haematite/__init__.py
haematite/runtime.py
haematite-0.1.0.dist-info/METADATA
haematite-0.1.0.dist-info/WHEEL
haematite-0.1.0.dist-info/licenses/LICENSE
haematite-0.1.0.dist-info/RECORD
