Metadata-Version: 2.4
Name: haematite
Version: 0.1.0
Summary: Runtime support for Haematite notebooks - variable extraction and export API
Project-URL: Homepage, https://github.com/tomWhiting/haematite
Project-URL: Repository, https://github.com/tomWhiting/haematite
Author: Haematite Contributors
License-Expression: MIT
License-File: LICENSE
Keywords: data-exploration,haematite,notebook,polyglot
Classifier: Development Status :: 3 - Alpha
Classifier: Intended Audience :: Developers
Classifier: License :: OSI Approved :: MIT License
Classifier: Programming Language :: Python :: 3
Classifier: Programming Language :: Python :: 3.9
Classifier: Programming Language :: Python :: 3.10
Classifier: Programming Language :: Python :: 3.11
Classifier: Programming Language :: Python :: 3.12
Requires-Python: >=3.9
Provides-Extra: dev
Requires-Dist: pytest>=7.0; extra == 'dev'
